{"url":"https://community.fantasyflightgames.com/topic/104678-roast-em-or-boil-em/","title":"Roast &#039;em or boil &#039;em","comments":[{"commentUrl":"https://community.fantasyflightgames.com/topic/104678-roast-em-or-boil-em/?do=findComment&comment=1060246","commentId":1060246,"userName":"Mndela","timestamp":1398330738,"content":"A question about his shadow:\n\n \n\nM1592.png [http://hallofbeorn.com/Images/Cards/M1592.png]\n\n \n\nText says: Shadow: Search the encounter deck for Troll Camp and add it to the staging area. Then, shuffle the encounter deck.\n\n \n\nThe question is about the 'then' theme. Like Caleb answered, it is only an effect that triggers if condition is triggered.\n\n \n\nWell, the problem was: there weren't Troll Camps in the encounter deck. And we had sent a troll to the bottom of the encounter deck by O Elbereth Gilthonial.\n\n \n\nM1494.png [http://hallofbeorn.com/Images/Cards/M1494.png]\n\n \n\nThe forum was open :) [//content.invisioncic.com/Mfantflight/emoticons/default_smile.png] : i said that we hadn't to shuffle the encounter deck because condition wasn't triggered (no troll camps in encounter deck); but other players said that it was so becasue we tried to search into the encounter deck, so first part was trigered even if no Troll Camps inside.\n\n \n\nWhat do you think? The 'Then...' text was triggered or not?\n\n "},{"commentUrl":"https://community.fantasyflightgames.com/topic/104678-roast-em-or-boil-em/?do=findComment&comment=1060252","commentId":1060252,"userName":"alogos","timestamp":1398331323,"content":"It's written in the rule that, whenever you search a card, you should shuffle.\n\n \n\nEdit: Or the faq :\n\n> (1.21) Search Effects\n> Whenever a player searches through a deck, that player\n> shuffles the deck after searching it unless a card effect\n> says otherwise. Players do not shuffle or change the\n> order of a discard pile after searching it.\n> \n>  \n\nEdited April 24, 2014 by alogos"}]}