{"url":"https://community.fantasyflightgames.com/topic/120716-the-lotr-lcg-atlas/","title":"The LOTR LCG Atlas","comments":[{"commentUrl":"https://community.fantasyflightgames.com/topic/120716-the-lotr-lcg-atlas/?do=findComment&comment=1238819","commentId":1238819,"userName":"Kerstoid","timestamp":1409402707,"content":"Over the summer, I started working on a new project building an interactive atlas of locations for our beloved card game.  As a lover of maps, I learned a lot building this and hope you will enjoy browsing it, reading my introductions, and seeing the locations laid out on the map of Middle-earth.\n\n \n\nSo far, I've only finished the core set and first two cycles, but hope to keep plugging away over the course of the year.  I'm not a web designer, but have found the free services of GoogleSites [https://sites.google.com/]and ThingLink [https://www.thinglink.com/] sufficient to my goals so far.  Go check it out and see what you think!\n\n \n\nBrowse through Master of Lore's LOTR LCG Atlas [https://sites.google.com/site/thelotrlcgatlas/].  Use links at the bottom of each page to advance in release order through the maps.\n\n \n\nGlimpse my Steward's Fear map [https://www.thinglink.com/scene/549575460619550722] (with locations, allies, and more).\n\n \n\nscreen-shot-2014-07-26-at-9-26-38-am.png [https://masteroflore.files.wordpress.com/2014/07/screen-shot-2014-07-26-at-9-26-38-am.png?w=957&amp;h=471]\n\nEdited August 30, 2014 by Kerstoid"},{"commentUrl":"https://community.fantasyflightgames.com/topic/120716-the-lotr-lcg-atlas/?do=findComment&comment=1238825","commentId":1238825,"userName":"Glaurung","timestamp":1409403245,"content":"WOW that cool stuff man!!!!  I like it  lot!"},{"commentUrl":"https://community.fantasyflightgames.com/topic/120716-the-lotr-lcg-atlas/?do=findComment&comment=1238884","commentId":1238884,"userName":"Jackelantern","timestamp":1409407443,"content":"unbelievably awesome! I will have to keep this open the next time i play! :D [//content.invisioncic.com/Mfantflight/emoticons/default_biggrin.png]"},{"commentUrl":"https://community.fantasyflightgames.com/topic/120716-the-lotr-lcg-atlas/?do=findComment&comment=1238971","commentId":1238971,"userName":"FetaCheese","timestamp":1409412946,"content":"Oh wow, well done! This looks amazing! Lotr LCG really has the best fanbase of them all."},{"commentUrl":"https://community.fantasyflightgames.com/topic/120716-the-lotr-lcg-atlas/?do=findComment&comment=1239201","commentId":1239201,"userName":"timbolton","timestamp":1409421328,"content":"Great stuff!"},{"commentUrl":"https://community.fantasyflightgames.com/topic/120716-the-lotr-lcg-atlas/?do=findComment&comment=1239271","commentId":1239271,"userName":"Mndela","timestamp":1409424409,"content":"Congrats, amazing job"},{"commentUrl":"https://community.fantasyflightgames.com/topic/120716-the-lotr-lcg-atlas/?do=findComment&comment=1239291","commentId":1239291,"userName":"CJMatos","timestamp":1409425120,"content":"Great job, Kerstoid"},{"commentUrl":"https://community.fantasyflightgames.com/topic/120716-the-lotr-lcg-atlas/?do=findComment&comment=1240037","commentId":1240037,"userName":"BoundForGlory","timestamp":1409471124,"content":"Very well done!  Thanks for sharing this with your fellow fans!"},{"commentUrl":"https://community.fantasyflightgames.com/topic/120716-the-lotr-lcg-atlas/?do=findComment&comment=1241578","commentId":1241578,"userName":"richsabre","timestamp":1409558876,"content":"excellent work my friend!!:) [//content.invisioncic.com/Mfantflight/emoticons/default_smile.png]"},{"commentUrl":"https://community.fantasyflightgames.com/topic/120716-the-lotr-lcg-atlas/?do=findComment&comment=1253616","commentId":1253616,"userName":"divinityofnumber","timestamp":1410188323,"content":"Awesome!"},{"commentUrl":"https://community.fantasyflightgames.com/topic/120716-the-lotr-lcg-atlas/?do=findComment&comment=1255257","commentId":1255257,"userName":"jormungandr","timestamp":1410276262,"content":"Great job!"},{"commentUrl":"https://community.fantasyflightgames.com/topic/120716-the-lotr-lcg-atlas/?do=findComment&comment=1256411","commentId":1256411,"userName":"rekath16","timestamp":1410348935,"content":"Thats an absolutely cool idea and great work, Kerstoid!"},{"commentUrl":"https://community.fantasyflightgames.com/topic/120716-the-lotr-lcg-atlas/?do=findComment&comment=1256468","commentId":1256468,"userName":"Tanarion","timestamp":1410352252,"content":"Tip of the hat to you! Excellent work."}]}