{"url":"https://community.fantasyflightgames.com/topic/128083-fords-of-isen-question/","title":"Fords of Isen Question","comments":[{"commentUrl":"https://community.fantasyflightgames.com/topic/128083-fords-of-isen-question/?do=findComment&comment=1350593","commentId":1350593,"userName":"Epi Lepi","timestamp":1417245482,"content":"In the setup of several parts of the quest it says \"Each player searches the encounter deck and discard pile for 1 different Dunland enemy and adds it to the staging area.\" Different means different types of enemy right? So you can't do 2 berserkers for example? Just want to make sure I'm not being too literal with the cards."},{"commentUrl":"https://community.fantasyflightgames.com/topic/128083-fords-of-isen-question/?do=findComment&comment=1350840","commentId":1350840,"userName":"GrandSpleen","timestamp":1417272963,"content":"That's how I understood it."}]}