{"url":"https://community.fantasyflightgames.com/topic/129110-quick-question/","title":"Quick Question","comments":[{"commentUrl":"https://community.fantasyflightgames.com/topic/129110-quick-question/?do=findComment&comment=1367588","commentId":1367588,"userName":"flipperlord","timestamp":1418613412,"content":"When placing tokens on the quest card, if I end up placing more tokens on it than it's level (forgive my lack of correct terminology), will the left over tokens be placed on the next quest card, or no?\n\n \n\nThanks! :) [//content.invisioncic.com/Mfantflight/emoticons/default_smile.png]"},{"commentUrl":"https://community.fantasyflightgames.com/topic/129110-quick-question/?do=findComment&comment=1367615","commentId":1367615,"userName":"lecudas","timestamp":1418615408,"content":"No. The new stage of the scenario starts without any progress tokens on it. See p.22 in the rule book (Quest Advancement): \"Additional progress tokens earned against the quest do not carry over to the next stage.\""},{"commentUrl":"https://community.fantasyflightgames.com/topic/129110-quick-question/?do=findComment&comment=1367616","commentId":1367616,"userName":"lecudas","timestamp":1418615477,"content":"Excess progress tokens placed on an active location, however, do carry over to the quest card."},{"commentUrl":"https://community.fantasyflightgames.com/topic/129110-quick-question/?do=findComment&comment=1369314","commentId":1369314,"userName":"flipperlord","timestamp":1418751511,"content":"Thank you very much!"}]}