{"url":"https://community.fantasyflightgames.com/topic/219175-flight-of-the-stormcaller/","title":"Flight of the Stormcaller","comments":[{"commentUrl":"https://community.fantasyflightgames.com/topic/219175-flight-of-the-stormcaller/?do=findComment&comment=2202262","commentId":2202262,"userName":"cmabr002","timestamp":1462468708,"content":"How long has it been available on the FFG page, Cool Stuff Inc., and Miniature Market?  Normally I see a news topic about it, but haven't seen one yet."},{"commentUrl":"https://community.fantasyflightgames.com/topic/219175-flight-of-the-stormcaller/?do=findComment&comment=2202394","commentId":2202394,"userName":"Slothgodfather","timestamp":1462472043,"content":"Looks like the product page was updated yesterday, but I hadn't heard anything from my local retailer about it yet and FFG hasn't made the usual news post either. Still no post from FFG but the product is in at my local retailer.\n\nEdited May 5, 2016 by Slothgodfather"},{"commentUrl":"https://community.fantasyflightgames.com/topic/219175-flight-of-the-stormcaller/?do=findComment&comment=2202408","commentId":2202408,"userName":"Slothgodfather","timestamp":1462472342,"content":"Side note, all the cards have been posted to the Cardgamedb deck builder."}]}