{"url":"https://community.fantasyflightgames.com/topic/311240-vilya-and-x-cost/","title":"Vilya and X cost","comments":[{"commentUrl":"https://community.fantasyflightgames.com/topic/311240-vilya-and-x-cost/?do=findComment&comment=3988248","commentId":3988248,"userName":"koriakin97","timestamp":1600112033,"content":"Hi\n\nDoes anybody know what happens when Vilya pulls X cost card? Does it treat it as 0, or can you choose any number?\n\nIf you can choose any number, Gandalf’s search would let you choose order of cards in whole your deck, making the card quite good. But it doesn’t sound like it’s allowed…"},{"commentUrl":"https://community.fantasyflightgames.com/topic/311240-vilya-and-x-cost/?do=findComment&comment=3988253","commentId":3988253,"userName":"Alonewolf87","timestamp":1600113541,"content":"> 24 minutes ago, koriakin97 said:\n> \n> Hi\n> \n> Does anybody know what happens when Vilya pulls X cost card? Does it treat it as 0, or can you choose any number?\n\nIf you play a card with X cost for no cost it's counted as 0."}]}