{"url":"https://community.fantasyflightgames.com/topic/45977-eowyn-action-question/","title":"Eowyn action question","comments":[{"commentUrl":"https://community.fantasyflightgames.com/topic/45977-eowyn-action-question/?do=findComment&comment=460955","commentId":460955,"userName":"blacksmith2","timestamp":1304066513,"content":"Hiya all :) [//content.invisioncic.com/Mfantflight/emoticons/default_smile.png]\n\nI have one question about Eowyn action. Card says that if we discard one card we will get +1 willpower.\n\nCan I discard 2 or 3 cards and get 2-3 willpower points or is it jus one point per discarded card per player ?"},{"commentUrl":"https://community.fantasyflightgames.com/topic/45977-eowyn-action-question/?do=findComment&comment=460970","commentId":460970,"userName":"Artumnis","timestamp":1304069607,"content":"No you cannot. Eowyn says that you may discard 1 card from your hand. So you get 1 willpower. Her effect may trigger each player once each round. It means she gets max 2 willpower per round. Everything important is written on the card."},{"commentUrl":"https://community.fantasyflightgames.com/topic/45977-eowyn-action-question/?do=findComment&comment=460989","commentId":460989,"userName":"sputang","timestamp":1304071747,"content":"Or +4 willpower in a 4 player game."},{"commentUrl":"https://community.fantasyflightgames.com/topic/45977-eowyn-action-question/?do=findComment&comment=461407","commentId":461407,"userName":"qwertyuiop","timestamp":1304160541,"content":" Or + 7 billion in a global player game."}]}