{"url":"https://community.fantasyflightgames.com/topic/51738-san-antonio-players/","title":"San Antonio Players! ","comments":[{"commentUrl":"https://community.fantasyflightgames.com/topic/51738-san-antonio-players/?do=findComment&comment=516077","commentId":516077,"userName":"Fenris Chosen2","timestamp":1313596020,"content":" I was curious about picking this up, but are there any other San Antonio players? "},{"commentUrl":"https://community.fantasyflightgames.com/topic/51738-san-antonio-players/?do=findComment&comment=517835","commentId":517835,"userName":"Keggy","timestamp":1313942709,"content":"There are a couple of us that meet at a boardgame meetup Thursday nights at Gamelot."},{"commentUrl":"https://community.fantasyflightgames.com/topic/51738-san-antonio-players/?do=findComment&comment=519449","commentId":519449,"userName":"Fenris Chosen2","timestamp":1314197684,"content":" Do you meet up regularly? "},{"commentUrl":"https://community.fantasyflightgames.com/topic/51738-san-antonio-players/?do=findComment&comment=519457","commentId":519457,"userName":"Keggy","timestamp":1314198722,"content":"Every thursday night, starting around 7.  We don't always play LOTR, game selection is more of a free-for-all, but if someone really wants to play something, they can usually be accommodated."},{"commentUrl":"https://community.fantasyflightgames.com/topic/51738-san-antonio-players/?do=findComment&comment=520605","commentId":520605,"userName":"Keggy","timestamp":1314415176,"content":"Which heroes do you use for your deck?  I can try to make something that will work with whats left over, since we can't all use the same heroes."}]}