{"url":"https://community.fantasyflightgames.com/topic/88418-bombur-hero/","title":"Bombur Hero","comments":[{"commentUrl":"https://community.fantasyflightgames.com/topic/88418-bombur-hero/?do=findComment&comment=839077","commentId":839077,"userName":"-nebur-","timestamp":1376429829,"content":"\"When counting the number of Dwarf characters you control, Bombur counts as two.\"\n\n \n\nDo you think that I can use his ability for this 2 cards?\n\n \n\nErebor Battle Master\n\n\"Erebor Battle Master gets +1 lotr-icon-atk.gif [http://deckbauer.telfador.net/assets/cardgames/icons/lotr-icon-atk.gif] for each other Dwarf character you control.\"\n\n \n\nWe are not idle\n\n\"Action: Exhaust X Dwarf characters to add X resources to a hero's resource pool and draw 1 card.\""},{"commentUrl":"https://community.fantasyflightgames.com/topic/88418-bombur-hero/?do=findComment&comment=839083","commentId":839083,"userName":"Khamul The Easterling","timestamp":1376430413,"content":"My guess is you would be able to use his ability on the Battle Master, but not on \"We are not Idle\".  \n\n \n\nKhamul\n\nP.S. How did you get the cool attack symbol?  "},{"commentUrl":"https://community.fantasyflightgames.com/topic/88418-bombur-hero/?do=findComment&comment=839094","commentId":839094,"userName":"-nebur-","timestamp":1376430961,"content":"With \"Idle\" I have doubts too...\n\n \n\nOh, nice...I copied the text from http://deckbauer.telfador.net/ [http://deckbauer.telfador.net/]. (great tool :D [//content.invisioncic.com/Mfantflight/emoticons/default_biggrin.png] )"},{"commentUrl":"https://community.fantasyflightgames.com/topic/88418-bombur-hero/?do=findComment&comment=839140","commentId":839140,"userName":"richsabre","timestamp":1376433990,"content":"i think idle was dealt with official in the FAQ or somewhere else. i am pretty sure he counts as 1\n\nrich"},{"commentUrl":"https://community.fantasyflightgames.com/topic/88418-bombur-hero/?do=findComment&comment=839151","commentId":839151,"userName":"-nebur-","timestamp":1376434456,"content":"Oh you´re right...I overlooked this.\n\n \n\nThanks"}]}